transportation/__init__.py
transportation/detection.py
transportation/sort.py
transportation/tracking.py
transportation/utils.py
transportation/visualization.py
track_transportation-0.0.6.dist-info/LICENSE
track_transportation-0.0.6.dist-info/METADATA
track_transportation-0.0.6.dist-info/WHEEL
track_transportation-0.0.6.dist-info/top_level.txt
track_transportation-0.0.6.dist-info/RECORD
