Metadata-Version: 2.1
Name: track_transportation
Version: 0.0.6
Summary: a small python project
Home-page: https://github.com/prthmgoyl/track_transportation
Author: prthmgoyl
Author-email: prthmgoyl@gmail.com
Project-URL: Bug Tracker, https://github.com/prthmgoyl/track_transportation/issues
License-File: LICENSE
Requires-Dist: numpy
Requires-Dist: opencv-python
Requires-Dist: torch
Requires-Dist: matplotlib
Requires-Dist: ultralytics
Requires-Dist: cvzone
Requires-Dist: tqdm
Requires-Dist: filterpy
Requires-Dist: scikit-image
